<GoodReadsResponse>
    <Request>
        <key/>
        <method/>
    </Request>
    <Author>
        <id>4432</id>
        <name/>
        <link>
        <![CDATA[
            https://www.goodreads.com/author/show/4432.Jasper_Fforde
        ]]>
        </link>
        <fans_count type="integer">7424</fans_cout>
        <author_followers_count type="integer">7424</>
        <lage_image_url>
        <![CDATA[
            https://images.gr-assets.com/authors/1350497674/4432.jpg
        ]]>
        </lage_image_url>
        <image_url/>
    </Author>>
</GoodReadsResponse>
